[{"investment_option_id":"12","investment_option_label":"Balanced Index","account_type_label":"Accumulation","effective_date":"2022-12-23","buy_price":"1.205516","sell_price":"1.203830"},{"investment_option_id":"10","investment_option_label":"Balanced Impact","account_type_label":"Accumulation","effective_date":"2022-12-23","buy_price":"1.531446","sell_price":"1.529304"},{"investment_option_id":"11","investment_option_label":"Renewables Plus","account_type_label":"Accumulation","effective_date":"2022-12-23","buy_price":"1.223626","sell_price":"1.221792"},{"investment_option_id":"15","investment_option_label":"Pension Balanced Growth","account_type_label":"Account-Based Pension","effective_date":"2022-12-23","buy_price":"1.556358","sell_price":"1.554180"}]