[{"investment_option_id":"12","investment_option_label":"Balanced Index","account_type_label":"Accumulation","effective_date":"2022-11-04","buy_price":"1.206523","sell_price":"1.204835"},{"investment_option_id":"10","investment_option_label":"Balanced Impact","account_type_label":"Accumulation","effective_date":"2022-11-04","buy_price":"1.530569","sell_price":"1.528427"},{"investment_option_id":"11","investment_option_label":"Renewables Plus","account_type_label":"Accumulation","effective_date":"2022-11-04","buy_price":"1.229420","sell_price":"1.227578"},{"investment_option_id":"15","investment_option_label":"Pension Balanced Growth","account_type_label":"Account-Based Pension","effective_date":"2022-11-04","buy_price":"1.555488","sell_price":"1.553312"}]