[{"investment_option_id":"13","investment_option_label":"High Growth","account_type_label":"Accumulation","effective_date":"2024-05-13","buy_price":"1.082160","sell_price":"1.081730"},{"investment_option_id":"12","investment_option_label":"Balanced Index","account_type_label":"Accumulation","effective_date":"2024-05-13","buy_price":"1.416890","sell_price":"1.416320"},{"investment_option_id":"10","investment_option_label":"Balanced Impact","account_type_label":"Accumulation","effective_date":"2024-05-13","buy_price":"1.746580","sell_price":"1.745880"},{"investment_option_id":"11","investment_option_label":"Renewables Plus","account_type_label":"Accumulation","effective_date":"2024-05-13","buy_price":"1.405920","sell_price":"1.405360"},{"investment_option_id":"15","investment_option_label":"Pension Balanced Growth","account_type_label":"Account-Based Pension","effective_date":"2024-05-13","buy_price":"1.893280","sell_price":"1.891770"}]