[{"investment_option_id":"12","investment_option_label":"Balanced Index","account_type_label":"Accumulation","effective_date":"2022-09-16","buy_price":"1.208279","sell_price":"1.206589"},{"investment_option_id":"10","investment_option_label":"Balanced Impact","account_type_label":"Accumulation","effective_date":"2022-09-16","buy_price":"1.534440","sell_price":"1.532294"},{"investment_option_id":"11","investment_option_label":"Renewables Plus","account_type_label":"Accumulation","effective_date":"2022-09-16","buy_price":"1.230291","sell_price":"1.228447"},{"investment_option_id":"15","investment_option_label":"Pension Balanced Growth","account_type_label":"Account-Based Pension","effective_date":"2022-09-16","buy_price":"1.548119","sell_price":"1.545953"}]