[{"investment_option_id":"12","investment_option_label":"Balanced Index","account_type_label":"Accumulation","effective_date":"2023-01-31","buy_price":"1.239190","sell_price":"1.237456"},{"investment_option_id":"10","investment_option_label":"Balanced Impact","account_type_label":"Accumulation","effective_date":"2023-01-31","buy_price":"1.566828","sell_price":"1.564636"},{"investment_option_id":"11","investment_option_label":"Renewables Plus","account_type_label":"Accumulation","effective_date":"2023-01-31","buy_price":"1.254993","sell_price":"1.253111"},{"investment_option_id":"15","investment_option_label":"Pension Balanced Growth","account_type_label":"Account-Based Pension","effective_date":"2023-01-31","buy_price":"1.602075","sell_price":"1.599833"}]